bumplus/__init__.py
bumplus/__main__.py
bumplus/bumplus.py
bumplus/cli.py
bumplus/constants.py
bumplus/errors.py
bumplus/filters.py
bumplus/utils.py
bumplus/version.py
bumplus-0.12.0.dist-info/LICENSE
bumplus-0.12.0.dist-info/METADATA
bumplus-0.12.0.dist-info/WHEEL
bumplus-0.12.0.dist-info/entry_points.txt
bumplus-0.12.0.dist-info/RECORD
