Metadata-Version: 2.1
Name: bumplus
Version: 0.12.0
Summary: Bump the version in the project files.
Home-page: https://github.com/dochang/bumplus
License: MIT
Author: Wade Zhang
Author-email: dochang@gmail.com
Requires-Python: >=3.8.1,<4.0.0
Classifier: License :: OSI Approved :: MIT License
Classifier: Operating System :: OS Independent
Classifier: Programming Language :: Python :: 3
Classifier: Programming Language :: Python :: 3.9
Classifier: Programming Language :: Python :: 3.10
Classifier: Programming Language :: Python :: 3.11
Classifier: Programming Language :: Python :: 3.12
Requires-Dist: jinja2 (>=3.1.2,<4.0.0)
Requires-Dist: pytoml (>=0.1.21,<0.2.0)
Project-URL: Bug Tracker, https://github.com/dochang/bumplus/issues
Project-URL: Repository, https://github.com/dochang/bumplus
